{
  "$schema": "https://json-schema.org/draft/2020-12/schema",
  "$id": "https://veupathdb.github.io/vdi-service/schema/vdi/lanes/reconciliation.json",
  "title": "Dataset Reconciliation Lane Config",
  "type": "object",
  "allOf": [
    {
      "$ref": "/vdi-service/schema/vdi/lanes/lane-common.json#"
    },
    {
      "properties": {
        "kafkaConsumerId": {
          "default": "reconciliation-lane-receive"
        },
        "kafkaProducerId": {
          "$ref": "/vdi-service/schema/vdi/lanes/lane-common.json#/$defs/kafkaProducerId",
          "default": "reconciliation-lane-send"
        },
        "memoryQueueSize": {
          "default": 10
        },
        "workerCount": {
          "default": 10
        },
        "eventChannel": {
          "default": "reconciliation-triggers"
        },
        "eventKey": {
          "default": "reconciliation-trigger"
        }
      }
    }
  ],
  "additionalProperties": false
}
